pydrake/__init__.py
pydrake/ddragon.py
pydrake/errors.py
pydrake/leaguev4.py
pydrake/matchv4.py
pydrake/pydrake.py
pydrake/summonerv4.py
pydrake-0.2.1.dist-info/METADATA
pydrake-0.2.1.dist-info/WHEEL
pydrake-0.2.1.dist-info/top_level.txt
pydrake-0.2.1.dist-info/RECORD
