Metadata-Version: 2.1
Name: pydrake
Version: 0.2.1
Summary: Experimental Python API Wrapper for the Riot Games API.
Home-page: https://github.com/JPadley18/pydrake
Author: Jacob Padley
Author-email: jacob5180@hotmail.co.uk
License: UNKNOWN
Download-URL: https://github.com/JPadley18/pydrake/archive/v0.2.1.tar.gz
Keywords: riot league legends wrapper api pydrake drake
Platform: UNKNOWN
Classifier: Development Status :: 3 - Alpha
Classifier: Programming Language :: Python :: 3.7
Classifier: Programming Language :: Python :: 3.6
Classifier: Programming Language :: Python :: 3.5
Requires-Python: >=3.5
